django_audit_log/__init__.py
django_audit_log/admin.py
django_audit_log/apps.py
django_audit_log/middleware.py
django_audit_log/mixins.py
django_audit_log/models.py
django_audit_log/test_django_audit_log.py
django_audit_log/tests.py
django_audit_log/user_agent_utils.py
django_audit_log/utils.py
django_audit_log/views.py
django_audit_log/management/__init__.py
django_audit_log/management/commands/__init__.py
django_audit_log/management/commands/migrate_user_agents.py
django_audit_log/management/commands/reimport_user_agents.py
django_audit_log/migrations/0001_initial.py
django_audit_log/migrations/0002_accesslog_user_agent.py
django_audit_log/migrations/0003_alter_accesslog_data_alter_accesslog_ip_and_more.py
django_audit_log/migrations/0004_alter_accesslog_user_agent_loguseragent_and_more.py
django_audit_log/migrations/0005_accesslog_in_always_log_urls_and_more.py
django_audit_log/migrations/0006_loguseragent_operating_system_version.py
django_audit_log/migrations/0007_merge_duplicate_paths.py
django_audit_log/migrations/0008_alter_loguseragent_browser_and_more.py
django_audit_log/migrations/0009_logpath_exclude_path_loguseragent_exclude_agent_and_more.py
django_audit_log/migrations/__init__.py
django_audit_log/templates/admin/django_audit_log/accesslog/change_list.html
catalpa_django_audit_log-0.0.7.dist-info/METADATA
catalpa_django_audit_log-0.0.7.dist-info/WHEEL
catalpa_django_audit_log-0.0.7.dist-info/entry_points.txt
catalpa_django_audit_log-0.0.7.dist-info/licenses/LICENSE
catalpa_django_audit_log-0.0.7.dist-info/RECORD
