Metadata-Version: 2.4
Name: catalpa-django-audit-log
Version: 0.0.7
Summary: Add your description here
Author-email: Josh Brooks <josh.vdbroek@gmail.com>
License-File: LICENSE
Requires-Python: >=3.11
Requires-Dist: django>=4
